inception_fid_weights_shard01/__init__.py
inception_fid_weights_shard01/shard-01.bin
inception_fid_weights_shard01-0.1.0.dist-info/METADATA
inception_fid_weights_shard01-0.1.0.dist-info/WHEEL
inception_fid_weights_shard01-0.1.0.dist-info/top_level.txt
inception_fid_weights_shard01-0.1.0.dist-info/RECORD
